fineuploader/__init__.py
fineuploader/admin.py
fineuploader/apps.py
fineuploader/backends.py
fineuploader/conf.py
fineuploader/formfields.py
fineuploader/forms.py
fineuploader/managers.py
fineuploader/models.py
fineuploader/urls.py
fineuploader/views.py
fineuploader/widgets.py
fineuploader/ajaxuploader/__init__.py
fineuploader/ajaxuploader/models.py
fineuploader/ajaxuploader/signals.py
fineuploader/ajaxuploader/views.py
fineuploader/ajaxuploader/backends/__init__.py
fineuploader/ajaxuploader/backends/base.py
fineuploader/ajaxuploader/backends/local.py
fineuploader/ajaxuploader/static/ajaxuploader/css/fileuploader.css
fineuploader/ajaxuploader/static/ajaxuploader/img/edit.gif
fineuploader/ajaxuploader/static/ajaxuploader/img/loading.gif
fineuploader/ajaxuploader/static/ajaxuploader/img/processing.gif
fineuploader/ajaxuploader/static/ajaxuploader/js/fileuploader.js
fineuploader/migrations/0001_initial.py
fineuploader/migrations/__init__.py
fineuploader/static/fineuploader/css/fineuploader.css
fineuploader/static/fineuploader/js/fineuploader.js
fineuploader/templates/fineuploader/fineinput.html
fineuploader/templates/fineuploader/fineuploader_css.html
fineuploader/templates/fineuploader/fineuploader_js.html
django_fineuploader-0.2.1.dist-info/AUTHORS
django_fineuploader-0.2.1.dist-info/LICENSE
django_fineuploader-0.2.1.dist-info/METADATA
django_fineuploader-0.2.1.dist-info/WHEEL
django_fineuploader-0.2.1.dist-info/top_level.txt
django_fineuploader-0.2.1.dist-info/RECORD
