Metadata-Version: 2.1
Name: django-fineuploader
Version: 0.2.1
Summary: Simple Fine Uploader integration for Django
Home-page: https://github.com/bashu/django-fineuploader
Author: Basil Shubin
Author-email: basil.shubin@gmail.com
License: BSD License, Version 3.0
Download-URL: https://github.com/bashu/django-fineuploader/zipball/master
Platform: UNKNOWN
Classifier: Development Status :: 4 - Beta
Classifier: Environment :: Web Environment
Classifier: Framework :: Django
Classifier: Intended Audience :: Developers
Classifier: License :: OSI Approved :: BSD License
Classifier: Operating System :: OS Independent
Classifier: Programming Language :: Python
Classifier: Programming Language :: Python :: 2.6
Classifier: Programming Language :: Python :: 2.7
Classifier: Programming Language :: Python :: 3
Classifier: Programming Language :: Python :: 3.3
Classifier: Topic :: Internet :: WWW/HTTP
Classifier: Topic :: Internet :: WWW/HTTP :: Dynamic Content
Classifier: Topic :: Software Development :: Libraries :: Python Modules
Requires: Django (>=1.8)
Requires-Dist: django-appconf
Requires-Dist: django-positions
Requires-Dist: django-attachments
Requires-Dist: pathlib
